{
  "users": [
    {
      "id": 1,
      "Login": 1,
      "Prénom": "Perfect",
      "Nom": "Cell",
      "Email": "perfect.cell@toriyama.jp",
      "Role": "VOYAGEUR",
      "Date-Heure": "Header:date-heure"
    },
    {
      "id": 2,
      "Login": 2,
      "Prénom": "Goku",
      "Nom": "Son",
      "Email": "son.goku@toriyama.jp",
      "Role": "VOYAGEUR",
      "Date-Heure": "Header:date-heure"
    }
  ],
  "droit": [
    {
      "id": 1,
      "ajouté par": {
        "Nom": "Kame sennin",
        "Prenom": "Tortue Géniale",
        "Email": "kame.sennin@toriyama.jp",
        "Role": "GESTIONNAIRE",
        "Date-Heure ajout": "Header:date-heure"
      },
      "hebergement": {
        "hebergement_id": 1,
        "hebergement_nom": "Kame House",
        "adresse": {
          "codePostal": "string",
          "pays": "string",
          "rue": "string",
          "ville": "string"
        }
      },
      "beneficiaire": {
        "login": 125,
        "date-deb": "08/08/2018",
        "date-fin": "10/08/2018"
      }
    },
    {
      "id": 2,
      "ajouté par": {
        "Nom": "Kame sennin",
        "Prenom": "Tortue Géniale",
        "Email": "kame.sennin@toriyama.jp",
        "Role": "GESTIONNAIRE",
        "Date-Heure ajout": "Header:date-heure"
      },
      "hebergement": {
        "hebergement_id": 1,
        "hebergement_nom": "Kame House",
        "adresse": {
          "codePostal": "string",
          "pays": "string",
          "rue": "string",
          "ville": "string"
        }
      },
      "beneficiaire": {
        "login": 126,
        "date-deb": "09/08/2018",
        "date-fin": "11/08/2018"
      }
    }
  ],
  "unlock": [
    {
      "id": 1,
      "hebergement": {
        "hebergement_id": 1,
        "hebergement_nom": "Kame House",
        "adresse": {
          "codePostal": "string",
          "pays": "string",
          "rue": "string",
          "ville": "string"
        },
        "access_id": 1,
        "date_heure": "header: date-heure",
        "demandeur": {
          "Login": 2,
          "Prénom": "Goku",
          "Nom": "Son",
          "Email": "son.goku@toriyama.jp",
          "Role": "VOYAGEUR"
        }
      }
    },
    {
      "id": 2,
      "hebergement": {
        "hebergement_id": 1,
        "hebergement_nom": "Kame House",
        "adresse": {
          "codePostal": "string",
          "pays": "string",
          "rue": "string",
          "ville": "string"
        },
        "access_id": 1,
        "date_heure": "header: date-heure",
        "demandeur": {
          "Login": 3,
          "Prénom": "Bulma",
          "Nom": "",
          "Email": "bulma@capsule.corp",
          "Role": "VOYAGEUR"
        }
      }
    }
  ]
}